DESCRIPTION.rst
MANIFEST.in
README.md
RELEASE-VERSION
setup.cfg
setup.py
version.py
elfcommander/__init__.py
elfcommander/elfcommander.py
elfcommander.egg-info/PKG-INFO
elfcommander.egg-info/SOURCES.txt
elfcommander.egg-info/dependency_links.txt
elfcommander.egg-info/entry_points.txt
elfcommander.egg-info/requires.txt
elfcommander.egg-info/top_level.txt