Metadata-Version: 1.1
Name: elfcommander
Version: 1.1.2
Summary: Interface to the Janelia Elf.
Home-page: https://github.com/janelia-pypi/elf_commander_python
Author: Peter Polidoro
Author-email: polidorop@janelia.hhmi.org
License: BSD
Keywords: elf elfcommander janelia modular_device bioshake
Platform: UNKNOWN
Classifier: Development Status :: 4 - Beta
Classifier: Intended Audience :: Developers
Classifier: Topic :: Software Development :: Build Tools
Classifier: License :: OSI Approved :: BSD License
Classifier: Programming Language :: Python :: 2.7
